Workbook

Sheet PORTADA
A1: MATRIZ DE RECOPILACIÓN DE DATOS — HUELLA DE CARBONO CORPORATIVA
A2: GHG Protocol (Corporate Standard) + ISO 14064-1:2018 | Sector Agropecuario
A4: IDENTIFICACIÓN DEL ESTABLECIMIENTO | F4: LÍMITES DEL INVENTARIO
A5: Razón Social / Nombre del Establecimiento | F5: Enfoque organizacional | G5: Control Operacional
A6: CUIT / RUT | F6: Alcance cubierto | G6: Scope 1 + Scope 2
A7: Provincia / Departamento | F7: ¿Incluye sumideros? | G7: Sí
A8: Dirección del establecimiento | F8: FE maquinaria/combustión | G8: IPCC 2006 / GHG Protocol
A9: Superficie total declarada (ha) | B9: 1.000 | F9: FE ganadería | G9: IPCC 2006 Tier 1/2
A10: Superficie productiva (ha) | B10: 900 | F10: FE electricidad | G10: Factor Red Argentina (CAMMESA)
A11: Año del inventario | F11: Factor red eléctrica (kg CO2e/kWh) | G11: 0,383
A12: Año base del inventario | F12: PRG CH4 — 100 años (AR6) | G12: 29,8
A13: Responsable del inventario | F13: PRG N2O — 100 años (AR6) | G13: 273
A14: Cargo / Matrícula profesional | F14: Unidad de reporte | G14: tCO2e / año
A15: Correo electrónico | F15: Versión del protocolo GHG | G15: Corporate Standard Rev. 2015
A16: Teléfono de contacto | F16: Norma de referencia | G16: ISO 14064-1:2018
A18: LEYENDA DE COLORES
A19: Celda de INGRESO DE DATOS (completar) | C19: Celda CALCULADA automáticamente | E19: Factor de Emisión de referencia | G19: Encabezado / Categoría
A21: FUENTES DE EMISIÓN Y SUMIDEROS DECLARADOS
A22: Código | B22: Fuente / Sumidero | E22: Descripción
A23: S1-1 | B23: Combustión Móvil
A24: S1-2 | B24: Combustión Estacionaria
A25: S1-3 | B25: Fermentación Entérica
A26: S1-4 | B26: Gestión de Estiércol
A27: S1-5 | B27: Suelos Agrícolas
A28: S1-6 | B28: Efluentes
A29: S2-1 | B29: Electricidad de Red
A30: SK-1 | B30: Sumideros

Sheet S1-1 MAQUINARIA
A1: SCOPE 1 — COMBUSTIÓN MÓVIL | Tractores, Cosechadoras y Camiones
A2: GHG Protocol — Mobile Combustion | IPCC 2006 Vol.2 Cap.3 | FE gasoil: 2,7 kg CO2/L | CH4: 0,1 g/MJ | N2O: 0,6 g/MJ
A4: N° | B4: Tipo de Máquina | C4: Marca / Modelo | D4: Año Fabric. | E4: Uso Anual (meses/año) | F4: Horas de Uso / mes [INGRESAR] | G4: Consumo promedio (L/hora) [INGRESAR] | H4: Consumo Total Anual (L) [CALC] | I4: FE CO2 (kg CO2/L) | J4: FE CH4 (g/L) | K4: FE N2O (g/L) | L4: CO2 (kg/año) | M4: CH4 (kg CO2e/año) | N4: N2O (kg CO2e/año) | O4: TOTAL tCO2e/año
A5: 1 | B5: Tractor | E5: 12 | H5: =F5*E5*G5 | I5: 2.701 | J5: 0.1 | K5: 0.6 | L5: =H5*I5 | M5: =H5*J5/1000*29.8 | N5: =H5*K5/1000*273 | O5: =(L5+M5+N5)/1000
A6: 2 | B6: Tractor | E6: 12 | H6: =F6*E6*G6 | I6: 2.701 | J6: 0.1 | K6: 0.6 | L6: =H6*I6 | M6: =H6*J6/1000*29.8 | N6: =H6*K6/1000*273 | O6: =(L6+M6+N6)/1000
A7: 3 | B7: Cosechadora | E7: 3 | H7: =F7*E7*G7 | I7: 2.701 | J7: 0.1 | K7: 0.6 | L7: =H7*I7 | M7: =H7*J7/1000*29.8 | N7: =H7*K7/1000*273 | O7: =(L7+M7+N7)/1000
A8: 4 | B8: Cosechadora | E8: 3 | H8: =F8*E8*G8 | I8: 2.701 | J8: 0.1 | K8: 0.6 | L8: =H8*I8 | M8: =H8*J8/1000*29.8 | N8: =H8*K8/1000*273 | O8: =(L8+M8+N8)/1000
A9: 5 | B9: Cosechadora | E9: 3 | H9: =F9*E9*G9 | I9: 2.701 | J9: 0.1 | K9: 0.6 | L9: =H9*I9 | M9: =H9*J9/1000*29.8 | N9: =H9*K9/1000*273 | O9: =(L9+M9+N9)/1000
A10: 6 | B10: Cosechadora | E10: 3 | H10: =F10*E10*G10 | I10: 2.701 | J10: 0.1 | K10: 0.6 | L10: =H10*I10 | M10: =H10*J10/1000*29.8 | N10: =H10*K10/1000*273 | O10: =(L10+M10+N10)/1000
A11: 7 | B11: Cosechadora | E11: 3 | H11: =F11*E11*G11 | I11: 2.701 | J11: 0.1 | K11: 0.6 | L11: =H11*I11 | M11: =H11*J11/1000*29.8 | N11: =H11*K11/1000*273 | O11: =(L11+M11+N11)/1000
A12: 8 | B12: Camión | E12: 12 | H12: =F12*E12*G12 | I12: 2.701 | J12: 0.1 | K12: 0.6 | L12: =H12*I12 | M12: =H12*J12/1000*29.8 | N12: =H12*K12/1000*273 | O12: =(L12+M12+N12)/1000
A13: 9 | B13: Camión | E13: 12 | H13: =F13*E13*G13 | I13: 2.701 | J13: 0.1 | K13: 0.6 | L13: =H13*I13 | M13: =H13*J13/1000*29.8 | N13: =H13*K13/1000*273 | O13: =(L13+M13+N13)/1000
A14: TOTAL COMBUSTIÓN MÓVIL | L14: =SUM(L5:L13) | M14: =SUM(M5:M13) | N14: =SUM(N5:N13) | O14: =SUM(O5:O13)
A16: NOTA: Para camiones con datos en km/año en lugar de horas, usar consumo en L/km y reemplazar columnas E y F por km/mes y L/km. FE gasoil = 2,701 kg CO2/L (IPCC 2006 Tabla 1.4). Si se usa biodiesel B5/B10, ajustar FE. Fuente de datos sugerida: planilla de control de combustible, remitos de surtidor o estimación por horas de horómetro.

Sheet S1-2 ENERGIA ESTAC
A1: SCOPE 1 — COMBUSTIÓN ESTACIONARIA | Generadores a Gasoil + Zeppelin GLP
A2: GHG Protocol — Stationary Combustion | IPCC 2006 Vol.2 Cap.2 | FE gasoil estacionario: 2,701 kg CO2/L | FE GLP: 2,983 kg CO2/kg
A3: SECCIÓN A — GENERADORES ELÉCTRICOS (Autogeneración a gasoil)
A4: N° | B4: Descripción / Ubicación | C4: Potencia (kW) | D4: Meses Oper. /año | E4: Horas Funcion. /mes [INGRESAR] | F4: Consumo promedio (L/hora) [INGRESAR] | G4: Consumo Total Anual (L) [CALC] | H4: kWh Generados /año [INGRESAR] | I4: FE CO2 (kg/L) | J4: CO2 (kg/año) | K4: CH4 (kg CO2e /año) | L4: TOTAL tCO2e/año
A5: 1 | B5: Generador principal | D5: 12 | G5: =E5*D5*F5 | I5: 2.701 | J5: =G5*I5 | K5: =G5*0.0001*29.8 | L5: =(J5+K5)/1000
A6: 2 | B6: Generador respaldo | D6: 12 | G6: =E6*D6*F6 | I6: 2.701 | J6: =G6*I6 | K6: =G6*0.0001*29.8 | L6: =(J6+K6)/1000
A7: SUBTOTAL GENERADORES | J7: =SUM(J5:J6) | K7: =SUM(K5:K6) | L7: =SUM(L5:L6)
A9: SECCIÓN B — ZEPPELIN DE GAS LICUADO DE PETRÓLEO (GLP / Propano-Butano)
A10: N° | B10: Descripción / Ubicación | C10: Capacidad Zeppelin (kg) | D10: Recargas por año [INGRESAR] | E10: kg GLP por recarga [INGRESAR] | F10: Consumo Total Anual (kg) [CALC] | G10: Litros equiv. /año [CALC] | H10: FE CO2 (kg CO2/kg GLP) | I10: CO2 (kg/año) | J10: CH4 (kg CO2e /año) | K10: N2O (kg CO2e /año) | L10: TOTAL tCO2e/año
A11: 1 | B11: Zeppelin GLP - instalaciones | F11: =D11*E11 | G11: =F11/0.51 | H11: 2.983 | I11: =F11*H11 | J11: =F11*0.001*29.8 | K11: =F11*0.0001*273 | L11: =(I11+J11+K11)/1000
A12: SUBTOTAL ZEPPELIN GLP | I12: =I11 | J12: =J11 | K12: =K11 | L12: =L11
A14: TOTAL COMBUSTIÓN ESTACIONARIA (Generadores + Zeppelin) | J14: =J7+I12 | K14: =K7+J12 | L14: =L7+L12
A16: NOTA: FE GLP (propano comercial) = 2,983 kg CO2/kg (IPCC 2006). Para determinar el consumo real, registrar las remisiones/facturas de recarga del zeppelin. Si no se cuenta con datos previos, instalar un horómetro en generadores y registrar litros en cada carga de combustible desde el inicio del período de reporte.

Sheet S1-3 GANADERIA
A1: SCOPE 1 — GANADERÍA | Fermentación Entérica + Gestión de Estiércol
A2: IPCC 2006 Vol.4 Cap.10/11 | Tier 1 por defecto — upgradeble a Tier 2 con datos de peso y dieta | PRG CH4 = 29,8 | PRG N2O = 273 (AR6, 100 años)
A3: SECCIÓN A — FERMENTACIÓN ENTÉRICA (CH4 ruminal)
A5: Categoría Animal | B5: Sistema Productivo | C5: Cabezas totales [INGRESAR] | D5: Días en estab. /año [INGRESAR] | E5: Cabezas equiv. (ajustado) [CALC] | F5: Peso vivo promedio (kg) [INGRESAR] | G5: FE CH4 Ferm.Ent. (kg CH4 /cab/año) [Tier 1] | H5: CH4 total (kg/año) [CALC] | I5: CH4 (kg CO2e /año) [CALC] | J5: Producción anual leche o carne [INGRESAR] | K5: Unidad | L5: Observaciones
A6: Vacas en ordeñe (tambo) | B6: Tambo | D6: 365 | E6: =C6*D6/365 | G6: 119.8 | H6: =E6*G6 | I6: =H6*29.8 | K6: L leche/día o kg carne/año
A7: Vaquillonas en ordeñe | B7: Tambo | D7: 365 | E7: =C7*D7/365 | G7: 100 | H7: =E7*G7 | I7: =H7*29.8 | K7: L leche/día o kg carne/año
A8: Novillos feedlot | B8: Feedlot | E8: =C8*D8/365 | G8: 56.5 | H8: =E8*G8 | I8: =H8*29.8 | K8: L leche/día o kg carne/año
A9: Novillitos feedlot | B9: Feedlot | E9: =C9*D9/365 | G9: 47.8 | H9: =E9*G9 | I9: =H9*29.8 | K9: L leche/día o kg carne/año
A10: Vaquillonas de recría | B10: Cría/Recría | D10: 365 | E10: =C10*D10/365 | G10: 47.8 | H10: =E10*G10 | I10: =H10*29.8 | K10: L leche/día o kg carne/año
A11: Terneros/as (dest.-12 meses) | B11: Cría | D11: 365 | E11: =C11*D11/365 | G11: 27 | H11: =E11*G11 | I11: =H11*29.8 | K11: L leche/día o kg carne/año
A12: Toros | B12: Cría/Tambo | D12: 365 | E12: =C12*D12/365 | G12: 73 | H12: =E12*G12 | I12: =H12*29.8 | K12: L leche/día o kg carne/año
A13: Ovinos / Caprinos | B13: Extensivo | D13: 365 | E13: =C13*D13/365 | G13: 8 | H13: =E13*G13 | I13: =H13*29.8 | K13: L leche/día o kg carne/año
A14: Cerdos (si aplica) | B14: Confinado | D14: 365 | E14: =C14*D14/365 | G14: 1.5 | H14: =E14*G14 | I14: =H14*29.8 | K14: L leche/día o kg carne/año
A15: Aves (si aplica) | B15: Confinado | D15: 365 | E15: =C15*D15/365 | G15: 0.02 | H15: =E15*G15 | I15: =H15*29.8 | K15: L leche/día o kg carne/año
A16: TOTAL FERMENTACIÓN ENTÉRICA | H16: =SUM(H6:H15) | I16: =SUM(I6:I15)
A18: SECCIÓN B — GESTIÓN DE ESTIÉRCOL (CH4 + N2O)
A19: Categoría Animal | B19: Sistema Productivo | C19: Cabezas [ref. Sec.A] [INGRESAR] | D19: Sistema de gestión estiércol | E19: % estiércol por sistema [INGRESAR] | F19: Temp. promedio anual (°C) [INGRESAR] | G19: FE CH4 estiércol (kg CH4 /cab/año) | H19: FE N2O estiércol (kg N2O /cab/año) | I19: CH4 (kg/año) [CALC] | J19: N2O (kg/año) [CALC] | K19: CH4 (kg CO2e /año) [CALC] | L19: N2O (kg CO2e /año) [CALC] | M19: TOTAL tCO2e/año [CALC] | N19: Observaciones
A20: Vacas en ordeñe (tambo) | B20: Tambo | D20: Laguna anaeróbica | E20: 100% | G20: 16 | H20: 0.1 | I20: =C20*G20 | J20: =C20*H20 | K20: =I20*29.8 | L20: =J20*273 | M20: =(K20+L20)/1000
A21: Novillos feedlot | B21: Feedlot | D21: Almac. sólido / corral | E21: 100% | G21: 1 | H21: 0.2 | I21: =C21*G21 | J21: =C21*H21 | K21: =I21*29.8 | L21: =J21*273 | M21: =(K21+L21)/1000
A22: Novillitos feedlot | B22: Feedlot | D22: Almac. sólido / corral | E22: 100% | G22: 1 | H22: 0.2 | I22: =C22*G22 | J22: =C22*H22 | K22: =I22*29.8 | L22: =J22*273 | M22: =(K22+L22)/1000
A23: Resto del rodeo (extensivo) | B23: Extensivo/pastoreo | D23: Pastoreo directo | E23: 100% | G23: 1 | H23: 0.07 | I23: =C23*G23 | J23: =C23*H23 | K23: =I23*29.8 | L23: =J23*273 | M23: =(K23+L23)/1000
A24: TOTAL GESTIÓN DE ESTIÉRCOL | I24: =SUM(I20:I23) | J24: =SUM(J20:J23) | K24: =SUM(K20:K23) | L24: =SUM(L20:L23) | M24: =SUM(M20:M23)
A26: NOTA Fermentación: FE Tier 1 para clima templado (FAO/IPCC 2006). Mejorar a Tier 2 cuando se disponga de peso vivo promedio por categoría y calidad de dieta. NOTA Estiércol: FE por defecto IPCC 2006 Tabla 10-14. La laguna anaeróbica de tambo es la fuente de mayor incertidumbre — verificar temperatura operativa. Las cabezas de la Sección B deben coincidir con las de la Sección A.

Sheet S1-4 SUELOS AGRICOLAS
A1: SCOPE 1 — SUELOS AGRÍCOLAS | N2O de Fertilizantes y Urea
A2: IPCC 2006 Vol.4 Cap.11 | EF1 (N directo) = 0,01 kg N2O-N/kg N aplicado | Emisión CO2 urea: 0,734 kg CO2/kg urea | EF3 (nitrificación/desnitrif.) incluido en cálculo indirecto
A4: Cultivo / Lote | B4: Campaña | C4: Superficie (ha) [INGRESAR] | D4: Fertil. N aplicado (kg N/ha) [INGRESAR] | E4: N total aplicado (kg N) [CALC] | F4: Urea aplicada (kg/ha) [INGRESAR] | G4: Urea total (kg) [CALC] | H4: Residuos cultivo incorpor. (t/ha) [INGRESAR] | I4: N en residuos (kg N) [CALC] | J4: EF1 N2O directo | K4: N2O directo (kg/año) [CALC] | L4: CO2 hidr. urea (kg CO2) [CALC] | M4: N2O total (kg CO2e/ año) [CALC] | N4: TOTAL tCO2e/año [CALC]
A5: Soja (1ra) | E5: =C5*D5 | G5: =C5*F5 | I5: =C5*H5*0.006 | J5: 0.01 | K5: =(E5+I5)*J5*(44/28) | L5: =G5*0.734 | M5: =K5*273 | N5: =(L5+M5)/1000
A6: Soja (2da) | E6: =C6*D6 | G6: =C6*F6 | I6: =C6*H6*0.006 | J6: 0.01 | K6: =(E6+I6)*J6*(44/28) | L6: =G6*0.734 | M6: =K6*273 | N6: =(L6+M6)/1000
A7: Maíz | E7: =C7*D7 | G7: =C7*F7 | I7: =C7*H7*0.006 | J7: 0.01 | K7: =(E7+I7)*J7*(44/28) | L7: =G7*0.734 | M7: =K7*273 | N7: =(L7+M7)/1000
A8: Trigo | E8: =C8*D8 | G8: =C8*F8 | I8: =C8*H8*0.006 | J8: 0.01 | K8: =(E8+I8)*J8*(44/28) | L8: =G8*0.734 | M8: =K8*273 | N8: =(L8+M8)/1000
A9: Sorgo forrajero | E9: =C9*D9 | G9: =C9*F9 | I9: =C9*H9*0.006 | J9: 0.01 | K9: =(E9+I9)*J9*(44/28) | L9: =G9*0.734 | M9: =K9*273 | N9: =(L9+M9)/1000
A10: Girasol | E10: =C10*D10 | G10: =C10*F10 | I10: =C10*H10*0.006 | J10: 0.01 | K10: =(E10+I10)*J10*(44/28) | L10: =G10*0.734 | M10: =K10*273 | N10: =(L10+M10)/1000
A11: Pasturas implantadas | E11: =C11*D11 | G11: =C11*F11 | I11: =C11*H11*0.006 | J11: 0.01 | K11: =(E11+I11)*J11*(44/28) | L11: =G11*0.734 | M11: =K11*273 | N11: =(L11+M11)/1000
A12: Otro cultivo 1 | E12: =C12*D12 | G12: =C12*F12 | I12: =C12*H12*0.006 | J12: 0.01 | K12: =(E12+I12)*J12*(44/28) | L12: =G12*0.734 | M12: =K12*273 | N12: =(L12+M12)/1000
A13: Otro cultivo 2 | E13: =C13*D13 | G13: =C13*F13 | I13: =C13*H13*0.006 | J13: 0.01 | K13: =(E13+I13)*J13*(44/28) | L13: =G13*0.734 | M13: =K13*273 | N13: =(L13+M13)/1000
A14: TOTAL SUELOS AGRÍCOLAS | J14: --- | K14: =SUM(K5:K13) | L14: =SUM(L5:L13) | M14: =SUM(M5:M13) | N14: =SUM(N5:N13)
A16: SECCIÓN B — EMISIONES ADICIONALES: AGROQUÍMICOS Y ENMIENDAS
A17: Los agroquímicos (herbicidas, fungicidas, insecticidas) no tienen FE estandarizado en IPCC para Scope 1. Se registran aquí para Scope 3 (emisiones upstream de fabricación) cuando se reporte esa categoría. Enmiendas calcáreas (cal, dolomita): FE = 0,44 kg CO2/kg cal; 0,477 kg CO2/kg dolomita.
A18: Insumo | B18: Tipo | C18: Cantidad Anual (kg o L) [INGRESAR] | D18: Unidad | E18: FE referencial (kg CO2/kg o L) | F18: Emisiones CO2 (kg/año) [CALC] | G18: Scope | H18: Observaciones
A19: Urea | B19: Fertilizante N | D19: kg | E19: Ya incluido en S A | F19: --- | G19: Scope 1 | H19: Hidrolisis: 0,734 kg CO2/kg
A20: Fertilizante N (otro) | B20: Fertilizante N | D20: kg N | E20: --- | F20: --- | G20: Scope 1 | H20: N directo en Sec A
A21: Herbicidas | B21: Agroquímico | D21: L | E21: No estandarizado | F21: --- | G21: Scope 3 | H21: Registrar para futuro Sc3
A22: Fungicidas | B22: Agroquímico | D22: L | E22: No estandarizado | F22: --- | G22: Scope 3 | H22: Registrar para futuro Sc3
A23: Insecticidas | B23: Agroquímico | D23: L | E23: No estandarizado | F23: --- | G23: Scope 3 | H23: Registrar para futuro Sc3
A24: Cal agrícola | B24: Enmienda | D24: kg | E24: 0,440 | F24: =C24*E24 | G24: Scope 1 | H24: Encalado: 0,44 kg CO2/kg
A25: Dolomita | B25: Enmienda | D25: kg | E25: 0,477 | F25: =C25*E25 | G25: Scope 1 | H25: Si se usa dolomita

Sheet S1-5 EFLUENTES
A1: SCOPE 1 — EFLUENTES LÍQUIDOS | Feedlot + Tambo
A2: IPCC 2006 Vol.5 Cap.6 | Bo (CH4 máx.) feedlot: 0,16 m³ CH4/kg DBO | EF efluentes N2O (Doering): 0,005 kg N2O-N/kg N efluente | Densidad CH4: 0,00067 t/m³
A4: Origen Efluente | B4: Sistema de Tratamiento | C4: Caudal diario (m³/día) [INGRESAR] | D4: Días operación /año [INGRESAR] | E4: Volumen anual (m³/año) [CALC] | F4: DBO afluente (mg/L) [INGRESAR] | G4: DBO Efluente (mg O2/L) [INGRESAR] | H4: Bo (m³ CH4 /kg DBO) | I4: MCF (Factor corr.) | J4: CH4 (m³/año) [CALC] | K4: CH4 (kg CO2e /año) [CALC] | L4: TOTAL tCO2e/año [CALC]
A5: Tambo — efluente sala ordeñe | B5: Laguna anaeróbica | D5: 365 | E5: =C5*D5 | H5: 0.16 | I5: 0.8 | J5: =E5*(F5-G5)/1000*H5*I5 | K5: =J5*0.00067*1000*29.8 | L5: =K5/1000
A6: Tambo — corrales y aguadas | B6: Laguna/infiltración | D6: 365 | E6: =C6*D6 | H6: 0.16 | I6: 0.3 | J6: =E6*(F6-G6)/1000*H6*I6 | K6: =J6*0.00067*1000*29.8 | L6: =K6/1000
A7: Feedlot — escorrentía corrales | B7: Laguna anaeróbica | D7: 365 | E7: =C7*D7 | H7: 0.16 | I7: 0.8 | J7: =E7*(F7-G7)/1000*H7*I7 | K7: =J7*0.00067*1000*29.8 | L7: =K7/1000
A8: Feedlot — aguas de bebederos | B8: Infiltración | D8: 200 | E8: =C8*D8 | H8: 0.08 | I8: 0.1 | J8: =E8*(F8-G8)/1000*H8*I8 | K8: =J8*0.00067*1000*29.8 | L8: =K8/1000
A9: TOTAL EFLUENTES | J9: =SUM(J5:J8) | K9: =SUM(K5:K8) | L9: =SUM(L5:L8)
A11: DATOS DE APOYO — TAMBO (completar para contexto)
A12: Vacas en ordeñe (promedio año) | E12: cabezas
A13: Producción leche por vaca (L/día) | E13: L/vaca/día
A14: Producción leche total (L/año) | E14: L/año — o CALC si los anteriores están completos
A15: Días de ordeñe por año | E15: días
A16: Tipo de sala de ordeñe | E16: rotativa, espina de pescado, etc.
A17: Sistema de lavado de sala | E17: agua fría/caliente, CIP, etc.
A18: Destino del efluente de sala | E18: laguna, compost, biodigestor, etc.
A20: DATOS DE APOYO — FEEDLOT (completar para contexto)
A21: Cabezas en engorde simultáneamente (promedio) | E21: cabezas
A22: Días promedio de estadía en feedlot | E22: días
A23: Entradas de hacienda por año (ciclos) | E23: ciclos/año
A24: Superficie total de corrales (m²) | E24: m²
A25: Sistema de drenaje | E25: describirlo
A26: Destino del estiércol sólido | E26: compost, esparcido, venta, etc.
A27: Capacidad laguna de efluentes (m³) | E27: m³

Sheet S2-1 ELECTRICIDAD
A1: SCOPE 2 — ELECTRICIDAD DE RED | Enfoque Basado en Localización
A2: GHG Protocol — Scope 2 Guidance (2015) | Factor de Emisión Red Argentina CAMMESA 2023: 0,383 kg CO2e/kWh | 20% del consumo eléctrico total es de red; 80% autogenerado (incluido en S1-2)
A4: Mes | B4: Año | C4: kWh facturados (red) [INGRESAR] | D4: Demanda punta (kW) [INGRESAR] | E4: Costo ($) [INGRESAR] | F4: N° Factura [INGRESAR] | G4: FE Red (kg CO2e /kWh) | H4: Emisiones CO2e (kg) [CALC] | I4: Emisiones CO2e (tCO2e) [CALC] | J4: Observaciones
A5: Enero | G5: 0.383 | H5: =C5*G5 | I5: =H5/1000
A6: Febrero | G6: 0.383 | H6: =C6*G6 | I6: =H6/1000
A7: Marzo | G7: 0.383 | H7: =C7*G7 | I7: =H7/1000
A8: Abril | G8: 0.383 | H8: =C8*G8 | I8: =H8/1000
A9: Mayo | G9: 0.383 | H9: =C9*G9 | I9: =H9/1000
A10: Junio | G10: 0.383 | H10: =C10*G10 | I10: =H10/1000
A11: Julio | G11: 0.383 | H11: =C11*G11 | I11: =H11/1000
A12: Agosto | G12: 0.383 | H12: =C12*G12 | I12: =H12/1000
A13: Septiembre | G13: 0.383 | H13: =C13*G13 | I13: =H13/1000
A14: Octubre | G14: 0.383 | H14: =C14*G14 | I14: =H14/1000
A15: Noviembre | G15: 0.383 | H15: =C15*G15 | I15: =H15/1000
A16: Diciembre | G16: 0.383 | H16: =C16*G16 | I16: =H16/1000
A17: TOTAL ANUAL | C17: =SUM(C5:C16) | D17: ELECTRICIDAD DE RED | H17: =SUM(H5:H16) | I17: =SUM(I5:I16)
A19: SECCIÓN B — AUTOGENERACIÓN (referencia cruzada con S1-2)
A20: Descripción | B20: Valor | C20: Fuente / Nota
A21: kWh generados por generadores (año) | D21: De hoja S1-2 col H
A22: kWh generados por otra fuente renovable | D22: Solar, eólico, etc.
A23: Total kWh consumidos en establecimiento (red + autogen.) | D23: Suma para contexto energético
A24: % autogeneración sobre consumo total | D24: Calc: autogen / (red + autogen)
A26: NOTA: Adjuntar copia de las 12 facturas eléctricas al expediente del inventario (requisito ISO 14064). Si no se dispone de medidor separado para carga de red, solicitar a la distribuidora histórico de consumo. Usar enfoque de market-based si se tiene contrato de energía renovable certificada (GO/REC).

Sheet SUMIDEROS
A1: SUMIDEROS DE CARBONO | Monte Nativo + Pasturas
A2: IPCC 2006 Vol.4 Cap.4/6 | Valores negativos = capturas (CO2 removido de la atmósfera) | Tier 1: factores por defecto por bioma/región. Para Tier 2 se requiere inventario forestal.
A3: SECCIÓN A — MONTE NATIVO / VEGETACIÓN PERENNE
A4: Unidad de Vegetación | B4: Tipo de Formación | C4: Superficie (ha) [INGRESAR] | D4: Estado de Conservación [INGRESAR] | E4: Categoría Ordenamiento Territorial (Ley 26.331) | F4: Biomasa aérea actual (t MS/ha) [INGRESAR] | G4: Factor de Captura Tier 1 (tCO2e/ha/año) | H4: Captura neta (tCO2e/año) [CALC] | I4: ¿Hay deforest.? [INGRESAR] | J4: ha deforest. este año [INGRESAR] | K4: Emisión deforest. (tCO2e) [CALC] | L4: Neto (tCO2e/año) [CALC]
A5: Bosque nativo sector Norte | B5: Bosque chaqueño / serrano | E5: Rojo / Amarillo | G5: 3.2 | H5: =-C5*G5 | I5: No | K5: =J5*G5*3.67 | L5: =H5+K5
A6: Bosque nativo sector Sur | B6: Bosque chaqueño / serrano | E6: Rojo / Amarillo | G6: 3.2 | H6: =-C6*G6 | I6: No | K6: =J6*G6*3.67 | L6: =H6+K6
A7: Monte ribereño / galería | B7: Bosque ribereño | E7: Rojo | G7: 4.5 | H7: =-C7*G7 | I7: No | K7: =J7*G7*3.67 | L7: =H7+K7
A8: Arbustales / malezales | B8: Matorral xerófilo | E8: Amarillo | G8: 1.5 | H8: =-C8*G8 | I8: No | K8: =J8*G8*3.67 | L8: =H8+K8
A9: SUBTOTAL MONTE NATIVO | H9: =SUM(H5:H8) | K9: =SUM(K5:K8) | L9: =SUM(L5:L8)
A11: SECCIÓN B — PASTURAS IMPLANTADAS Y SUELO BAJO AGRICULTURA
A12: Tipo de Pastura / Cultivo de Cobertura | B12: Manejo | C12: Superficie (ha) [INGRESAR] | D12: Años de establecida [INGRESAR] | E12: Estado Masomenos [INGRESAR] | F12: Labranza predominante [INGRESAR] | G12: FE Stock C suelo (tCO2e/ha/año) [Tier1] | H12: Captura neta (tCO2e/año) [CALC] | I12: Observaciones
A13: Pasturas implantadas perennes | B13: Pastoreo rotativo | F13: Sin labranza | G13: 0.5 | H13: =-C13*G13
A14: Pasturas anuales / verdeos | B14: Pastoreo continuo | F14: Siembra directa | G14: 0.2 | H14: =-C14*G14
A15: Cultivos anuales (soja/maíz/trigo) | B15: Agricultura | F15: Siembra directa | G15: 0.3 | H15: =-C15*G15
A16: Rastrojos incorporados | B16: Cobertura | F16: SD / Mín. labranza | G16: 0.15 | H16: =-C16*G16
A17: SUBTOTAL PASTURAS Y SUELOS | H17: =SUM(H13:H16)
A19: TOTAL SUMIDEROS (Monte + Pasturas) | H19: =H9+H17 | L19: =L9
A21: NOTA: Valores NEGATIVOS = capturas netas (el establecimiento absorbe CO2). Valores POSITIVOS = fuentes. Para inventario forestal verificado (VCS/Carbono Neutro) se requiere medición in situ (Tier 2/3). Factor de deforestación: 3,67 = relación masa molar CO2/C. Ley 26.331: bosques Rojo = no modificar; Amarillo = uso sostenible; Verde = aprovechamiento permitido. Los pastizales de siembra directa con más de 5 años tienden a ser sumideros netos.

Sheet FACTORES EMISION
A1: TABLA DE FACTORES DE EMISIÓN DE REFERENCIA
A2: Fuentes: IPCC 2006 | GHG Protocol | CAMMESA 2023 | AR6 IPCC 2021 — NO modificar esta hoja. Solo lectura.
A4: COMBUSTIBLES
A5: Gas / Fuente | B5: Aplicación | C5: Unidad | D5: FE CO2 (kg CO2/unidad) | E5: FE CH4 (g/unidad) | F5: FE N2O (g/unidad) | G5: Fuente
A6: Gasoil / Diésel | B6: Combustión móvil y estacionaria | C6: L | D6: 2,701 | E6: 0,100 | F6: 0,600 | G6: IPCC 2006 Tabla 1.4
A7: GLP / Propano (Zeppelin) | B7: Combustión estacionaria | C7: kg | D7: 2,983 | E7: 0,010 | F7: 0,100 | G7: IPCC 2006 Tabla 1.4
A8: Propano líquido | B8: Combustión estacionaria | C8: L | D8: 1,534 | E8: 0,010 | F8: 0,100 | G8: IPCC 2006 Tabla 1.4
A9: Gasolina / Nafta | B9: Combustión móvil | C9: L | D9: 2,296 | E9: 0,100 | F9: 0,600 | G9: IPCC 2006 Tabla 1.4
A10: Gas natural | B10: Combustión estacionaria | C10: m³ | D10: 1,879 | E10: 0,005 | F10: 0,010 | G10: IPCC 2006 Tabla 1.4
A12: ELECTRICIDAD
A13: Gas / Fuente | B13: Aplicación | C13: Unidad | D13: FE CO2 (kg CO2/unidad) | E13: FE CH4 (g/unidad) | F13: FE N2O (g/unidad) | G13: Fuente
A14: Red eléctrica Argentina (CAMMESA 2023) | B14: Scope 2 — factor de emisión localización | C14: kWh | D14: 0,383 | E14: — | F14: — | G14: CAMMESA — Factor de Emisión 2023
A15: Red eléctrica Argentina (CAMMESA 2022) | B15: Referencia histórica | C15: kWh | D15: 0,404 | E15: — | F15: — | G15: CAMMESA — Factor de Emisión 2022
A17: GANADERÍA — FERMENTACIÓN ENTÉRICA (Tier 1, clima templado)
A18: Gas / Fuente | B18: Aplicación | C18: Unidad | D18: FE CO2 (kg CO2/unidad) | E18: FE CH4 (g/unidad) | F18: FE N2O (g/unidad) | G18: Fuente
A19: Vacas lecheras (>200 L/día producción) | B19: Fermentación entérica | C19: cab/año | D19: 119,8 kg CH4 | E19: — | F19: — | G19: IPCC 2006 Tabla 10-11
A20: Bovinos adultos carne (>300 kg) | B20: Fermentación entérica | C20: cab/año | D20: 56,5 kg CH4 | E20: — | F20: — | G20: IPCC 2006 Tabla 10-11
A21: Novillo / vaquillona recría (200-300 kg) | B21: Fermentación entérica | C21: cab/año | D21: 47,8 kg CH4 | E21: — | F21: — | G21: IPCC 2006 Tabla 10-11
A22: Terneros < 1 año | B22: Fermentación entérica | C22: cab/año | D22: 27,0 kg CH4 | E22: — | F22: — | G22: IPCC 2006 Tabla 10-11
A23: Toros reproductores | B23: Fermentación entérica | C23: cab/año | D23: 73,0 kg CH4 | E23: — | F23: — | G23: IPCC 2006 Tabla 10-11
A24: Ovinos (adultos) | B24: Fermentación entérica | C24: cab/año | D24: 8,0 kg CH4 | E24: — | F24: — | G24: IPCC 2006 Tabla 10-11
A26: GANADERÍA — GESTIÓN DE ESTIÉRCOL (Tier 1)
A27: Gas / Fuente | B27: Aplicación | C27: Unidad | D27: FE CO2 (kg CO2/unidad) | E27: FE CH4 (g/unidad) | F27: FE N2O (g/unidad) | G27: Fuente
A28: Vacas lecheras — laguna anaeróbica | B28: CH4 estiércol | C28: cab/año | D28: 16,0 kg CH4 | E28: — | F28: 0,10 kg N2O | G28: IPCC 2006 Tabla 10-14/15
A29: Bovinos carne — almac. sólido/corral | B29: CH4 estiércol | C29: cab/año | D29: 1,0 kg CH4 | E29: — | F29: 0,20 kg N2O | G29: IPCC 2006 Tabla 10-14/15
A30: Bovinos — pastoreo directo | B30: CH4 estiércol | C30: cab/año | D30: 1,0 kg CH4 | E30: — | F30: 0,07 kg N2O | G30: IPCC 2006 Tabla 10-14/15
A32: SUELOS AGRÍCOLAS
A33: Gas / Fuente | B33: Aplicación | C33: Unidad | D33: FE CO2 (kg CO2/unidad) | E33: FE CH4 (g/unidad) | F33: FE N2O (g/unidad) | G33: Fuente
A34: Fertilizante N (nitrogenado) | B34: N2O directo suelos EF1 | C34: kg N aplic. | D34: 0,01 kg N2O-N | E34: — | F34: — | G34: IPCC 2006 Tabla 11-1
A35: Urea aplicada | B35: CO2 hidrólisis | C35: kg urea | D35: 0,734 kg CO2 | E35: — | F35: — | G35: IPCC 2006 Vol.4 Cap.11
A36: Residuos de cultivos incorporados | B36: N2O indirecto | C36: kg N residuos | D36: 0,01 kg N2O-N | E36: — | F36: — | G36: IPCC 2006 Tabla 11-1
A38: POTENCIALES DE CALENTAMIENTO GLOBAL (AR6 — 100 años)
A39: Gas / Fuente | B39: Aplicación | C39: Unidad | D39: FE CO2 (kg CO2/unidad) | E39: FE CH4 (g/unidad) | F39: FE N2O (g/unidad) | G39: Fuente
A40: CH4 (metano) | B40: GWP base CO2 | C40: kg CH4 | D40: 29,8 kg CO2e | E40: — | F40: — | G40: IPCC AR6 2021 Tabla 7.SM.7
A41: N2O (óxido nitroso) | B41: GWP base CO2 | C41: kg N2O | D41: 273 kg CO2e | E41: — | F41: — | G41: IPCC AR6 2021 Tabla 7.SM.7
A42: CO2 (dióxido de carbono) | B42: GWP base CO2 | C42: kg CO2 | D42: 1 kg CO2e | E42: — | F42: — | G42: Línea base

Sheet RESUMEN DASHBOARD
A1: RESUMEN DEL INVENTARIO DE GASES DE EFECTO INVERNADERO | HUELLA DE CARBONO CORPORATIVA
A2: Este resumen se actualiza automáticamente al completar las hojas de datos. Usar esta hoja como fuente del dashboard interactivo.
A4: TABLA 1 — EMISIONES Y CAPTURAS POR CATEGORÍA
A5: Código | B5: Categoría | C5: Scope | D5: CO2 (tCO2/año) | E5: CH4 (tCO2e/año) | F5: N2O (tCO2e/año) | G5: TOTAL tCO2e/año | H5: % del total emisiones | I5: Hoja de Referencia | J5: Observaciones
A6: S1-1 | B6: Combustión Móvil (maquinaria) | C6: Scope 1 | D6: =IFERROR('S1-1 MAQUINARIA'!O14,0) | E6: ver hoja | F6: ver hoja | G6: =D6 | H6: =IFERROR(G6/G13*100,0) | I6: S1-1 MAQUINARIA
A7: S1-2 | B7: Combustión Estacionaria (gen. + zeppelin) | C7: Scope 1 | D7: =IFERROR('S1-2 ENERGIA ESTAC'!L14,0) | E7: ver hoja | F7: ver hoja | G7: =D7 | H7: =IFERROR(G7/G13*100,0) | I7: S1-2 ENERGIA ESTAC
A8: S1-3 | B8: Fermentación Entérica | C8: Scope 1 | D8: =IFERROR('S1-3 GANADERIA'!I16,0) | E8: ver hoja | F8: ver hoja | G8: =D8 | H8: =IFERROR(G8/G13*100,0) | I8: S1-3 GANADERIA
A9: S1-4 | B9: Gestión de Estiércol | C9: Scope 1 | D9: =IFERROR('S1-3 GANADERIA'!M24,0) | E9: ver hoja | F9: ver hoja | G9: =D9 | H9: =IFERROR(G9/G13*100,0) | I9: S1-3 GANADERIA
A10: S1-5 | B10: Suelos Agrícolas (N2O + CO2 urea) | C10: Scope 1 | D10: =IFERROR('S1-4 SUELOS AGRICOLAS'!N14,0) | E10: ver hoja | F10: ver hoja | G10: =D10 | H10: =IFERROR(G10/G13*100,0) | I10: S1-4 SUELOS AGRICOLAS
A11: S1-6 | B11: Efluentes (feedlot + tambo) | C11: Scope 1 | D11: =IFERROR('S1-5 EFLUENTES'!L9,0) | E11: ver hoja | F11: ver hoja | G11: =D11 | H11: =IFERROR(G11/G13*100,0) | I11: S1-5 EFLUENTES
A12: S2-1 | B12: Electricidad de Red | C12: Scope 2 | D12: =IFERROR('S2-1 ELECTRICIDAD'!I17,0) | E12: ver hoja | F12: ver hoja | G12: =D12 | H12: =IFERROR(G12/G13*100,0) | I12: S2-1 ELECTRICIDAD
A13: SUBTOTAL EMISIONES (S1 + S2) | G13: =SUM(G6:G12)
A15: TABLA 2 — CAPTURAS (SUMIDEROS)
A16: Código | B16: Categoría | C16: Scope | D16: CO2 (tCO2/año) | E16: CH4 (tCO2e/año) | F16: N2O (tCO2e/año) | G16: TOTAL tCO2e/año | H16: % del total emisiones | I16: Hoja de Referencia | J16: Observaciones
A17: SK-1 | B17: Monte Nativo | C17: Sumidero | D17: =IFERROR(SUMIDEROS!H9,0) | G17: =D17 | I17: SUMIDEROS
A18: SK-2 | B18: Pasturas Implantadas | C18: Sumidero | D18: =IFERROR(SUMIDEROS!H17,0) | G18: =D18 | I18: SUMIDEROS
A19: SUBTOTAL CAPTURAS (Sumideros) | G19: =SUM(G17:G18)
A21: HUELLA DE CARBONO NETA (Emisiones + Capturas) | G21: =G13+G19 | H21: tCO2e/año
A23: TABLA 3 — INDICADORES DE INTENSIDAD (KPIs para Dashboard)
A24: Código | B24: Indicador | C24: Fórmula / Valor [CALC] | D24: Unidad | E24: Valor ingresado (si aplica) | J24: Notas
A25: KPI-01 | B25: Intensidad por hectárea productiva | C25: =G21/900 | D25: tCO2e/ha
A26: KPI-02 | B26: Intensidad de emisiones Scope 1 | C26: =SUM(G6:G11)/G13*100 | D26: % sobre total
A27: KPI-03 | B27: Intensidad de emisiones Scope 2 | C27: =G12/G13*100 | D27: % sobre total
A28: KPI-04 | B28: Proporción capturada por sumideros | C28: =IFERROR(ABS(G19)/G13*100,0) | D28: % capturas/emisiones
A29: KPI-05 | B29: Huella por cabeza ganadera (ingresar total cabezas) | C29: =IFERROR(G21/D28,0) | D29: tCO2e/cabeza/año
A30: KPI-06 | B30: Huella por tonelada de grano producida (ingresar prod.) | C30: =IFERROR(G21/E28,0) | D30: tCO2e/t grano
A31: KPI-07 | B31: Captura neta de sumideros (valor absoluto) | C31: =ABS(G19) | D31: tCO2e capturas/año
A32: KPI-08 | B32: Balance carbono (positivo = emisor neto) | C32: =G21 | D32: tCO2e neto/año
A33: DATOS AUXILIARES PARA KPIs (ingresar al final del período)
A34: Total de cabezas de ganado (promedio anual) | D34: cabezas | E34: Para KPI-05
A35: Producción total de granos (t/año) | D35: toneladas | E35: Para KPI-06
A36: Litros de leche producidos (L/año) | D36: litros/año | E36: Para tambo
A37: Kg de carne producidos (kg res/año) | D37: kg res/año | E37: Para feedlot
A38: Ingresos totales del establecimiento ($/año) | D38: $ | E38: Opcional: para huella por $ facturado
